async_loki_handler/__init__.py
async_loki_handler/async_loki_handler.py
async_loki_handler-0.0.9.dist-info/licenses/LICENSE
async_loki_handler-0.0.9.dist-info/METADATA
async_loki_handler-0.0.9.dist-info/WHEEL
async_loki_handler-0.0.9.dist-info/top_level.txt
async_loki_handler-0.0.9.dist-info/RECORD
