Metadata-Version: 2.4
Name: async_loki_handler
Version: 0.0.9
Summary: Handler для библиотек logging и loguru для отправки логов в Loki, поддерживает ассинхронную отправку батчами в отличии от конкрутенов
Author-email: Limby <bogo44tor@gmail.com>
License: MIT
Requires-Python: >=3.10
License-File: LICENSE
Requires-Dist: loguru>=0.7.3
Requires-Dist: aiohttp==3.13.0
Dynamic: license-file
